checkphone/__init__.py
checkphone/checkphone.py
checkphone/libs/checkphone
vuln_checkphone-0.1.7.dist-info/METADATA
vuln_checkphone-0.1.7.dist-info/WHEEL
vuln_checkphone-0.1.7.dist-info/top_level.txt
vuln_checkphone-0.1.7.dist-info/RECORD
