Metadata-Version: 2.1
Name: vuln-checkphone
Version: 0.1.7
Summary: YEah
Author: Jarle Kittilsen
Author-email: jarle.spam@gmail.com
License: MIT License
Classifier: License :: OSI Approved :: MIT License
Classifier: Programming Language :: Python :: 3
